aigent_lib/__init__.py
aigent_lib/app.py
aigent_lib/cli.py
aigent_lib/main.py
aigent_lib-0.1.0.dist-info/LICENSE
aigent_lib-0.1.0.dist-info/METADATA
aigent_lib-0.1.0.dist-info/WHEEL
aigent_lib-0.1.0.dist-info/entry_points.txt
aigent_lib-0.1.0.dist-info/top_level.txt
aigent_lib-0.1.0.dist-info/RECORD
