Metadata-Version: 2.2
Name: aigent-lib
Version: 0.1.0
Summary: An open-source project designed to streamline the process of developing AI applications
Home-page: https://https://github.com/enendufrankc/AiGen
Author: Frank Enendu
Author-email: frank@favai.onmicrosoft.com
Classifier: Programming Language :: Python :: 3
Classifier: License :: OSI Approved :: MIT License
Classifier: Operating System :: OS Independent
Requires-Python: >=3.11
License-File: LICENSE
Dynamic: author
Dynamic: author-email
Dynamic: classifier
Dynamic: description
Dynamic: description-content-type
Dynamic: home-page
Dynamic: requires-python
Dynamic: summary
